colorido/__init__.py
colorido/background.py
colorido/color.py
colorido/foreground.py
colorido/style.py
colorido-1.0.0.dist-info/LICENSE
colorido-1.0.0.dist-info/METADATA
colorido-1.0.0.dist-info/WHEEL
colorido-1.0.0.dist-info/top_level.txt
colorido-1.0.0.dist-info/RECORD
