Metadata-Version: 2.1
Name: colorido
Version: 1.0.0
Summary: A small lib to ease the coloring of your Terminal text logs with ANSI colors
Author-email: Italo Campos <italo.ramon.campos@gmail.com>
License: Copyright (c) 2020 Italo Campos        
Project-URL: Homepage, https://github.com/italocampos/colorido
Keywords: color,terminal,colored
Classifier: Development Status :: 5 - Production/Stable
Classifier: Environment :: Console
Classifier: License :: OSI Approved :: MIT License
Classifier: Operating System :: POSIX :: Linux
Classifier: Programming Language :: Python
Classifier: Programming Language :: Python :: 3.7
Requires-Python: >=3.7
License-File: LICENSE
Provides-Extra: dev
Requires-Dist: flake8 ; extra == 'dev'
